setup.py
dist17.egg-info/PKG-INFO
dist17.egg-info/SOURCES.txt
dist17.egg-info/dependency_links.txt
dist17.egg-info/not-zip-safe
dist17.egg-info/top_level.txt
distributions/Binominaldistribution.py
distributions/Gaussiandistribution.py
distributions/Generaldistriubtion.py
distributions/__init__.py
distributions/example_code.py
test/test.py