Metadata-Version: 2.1
Name: dist17
Version: 0.1
Summary: Gaussian and Binomial distributions
Home-page: 
Author: Donald Kelly
Author-email: myemail017@gmail.com
License: UNKNOWN
Platform: UNKNOWN
